LICENSE
README.md
setup.cfg
setup.py
elflepton.egg-info/PKG-INFO
elflepton.egg-info/SOURCES.txt
elflepton.egg-info/dependency_links.txt
elflepton.egg-info/top_level.txt
lepton/__init__.py
lepton/elfheader.py
lepton/elfprogramheader.py
lepton/elfsectionheader.py
lepton/embeddedelf.py
lepton/lepton.py
lepton/arch/__init__.py
lepton/arch/amd64.py
lepton/arch/arm.py
lepton/arch/i386.py
lepton/arch/mappings.py
lepton/arch/mips.py
lepton/arch/ppc.py
lepton/utils/__init__.py
lepton/utils/constants.py
lepton/utils/exceptions.py
lepton/utils/structures.py