Metadata-Version: 2.1
Name: elflepton
Version: 2.0.4
Summary: Parse an ELF binary with corrupted ELF headers.
Home-page: https://github.com/nikhilh-20/lepton
Author: Nikhil Ashok Hegde
Author-email: nikhilhegde20@gmail.com
License: MIT
License-File: LICENSE
